Metadata-Version: 2.1
Name: ruan-image-processing
Version: 0.0.1
Summary: Image Processing Package using Skimage
Home-page: https://github.com/RuanSpinelli/image-processing-package
Author: Ruan Spinelli
Requires-Python: >= 3.5
Requires-Dist: matplotlib
Requires-Dist: numpy
Requires-Dist: scikit-image>=0.16.1
